h5typer/__init__.py
h5typer/io.py
h5typer-0.2.0.dist-info/licenses/LICENSE
h5typer-0.2.0.dist-info/METADATA
h5typer-0.2.0.dist-info/WHEEL
h5typer-0.2.0.dist-info/top_level.txt
h5typer-0.2.0.dist-info/RECORD
