Metadata-Version: 2.4
Name: h5typer
Version: 0.2.0
Summary: Automatic type mapping for Python objects to HDF5
Author-email: Justin Chan <chan.waisoon@qst.go.jp>, Hidetoshi Kono <kono.hidetoshi@qst.go.jp>
License-Expression: MIT
Project-URL: Homepage, https://github.com/iQLS-MMS/h5typer
Keywords: hdf5,type-mapping,numpy,pandas,serialization
Classifier: Development Status :: 4 - Beta
Classifier: Intended Audience :: Science/Research
Classifier: Intended Audience :: Developers
Classifier: Topic :: Scientific/Engineering
Classifier: Topic :: Software Development :: Libraries :: Python Modules
Classifier: Programming Language :: Python :: 3
Classifier: Programming Language :: Python :: 3.10
Classifier: Programming Language :: Python :: 3.11
Classifier: Programming Language :: Python :: 3.12
Classifier: Programming Language :: Python :: 3.13
Classifier: Programming Language :: Python :: 3.14
Classifier: Operating System :: OS Independent
Requires-Python: >=3.10
License-File: LICENSE
Requires-Dist: numpy>=1.19.0
Requires-Dist: pandas>=1.0.0
Requires-Dist: h5py>=3.0.0
Dynamic: license-file
